<annotation>
  <filename>001159.jpg</filename>
  <size>
    <width>77</width>
    <height>67</height>
    <depth>3</depth>
  </size>
  <object>
    <name>three</name>
    <difficult>0</difficult>
    <bndbox>
      <xmin>19.3</xmin>
      <ymin>19.013650920948734</ymin>
      <xmax>37.3</xmax>
      <ymax>46.91869557169521</ymax>
    </bndbox>
  </object>
<object>
    <name>four</name>
    <difficult>0</difficult>
    <bndbox>
      <xmin>38.35</xmin>
      <ymin>20.010650887376812</ymin>
      <xmax>56.35</xmax>
      <ymax>47.915695538123295</ymax>
    </bndbox>
  </object>
</annotation>