<annotation>
  <filename>001581.jpg</filename>
  <size>
    <width>89</width>
    <height>51</height>
    <depth>3</depth>
  </size>
  <object>
    <name>zero</name>
    <difficult>0</difficult>
    <bndbox>
      <xmin>17.9</xmin>
      <ymin>18.61540112278754</ymin>
      <xmax>25.9</xmax>
      <ymax>30.0190136550314</ymax>
    </bndbox>
  </object>
<object>
    <name>four</name>
    <difficult>0</difficult>
    <bndbox>
      <xmin>26.95</xmin>
      <ymin>19.08904152678618</ymin>
      <xmax>34.95</xmax>
      <ymax>30.492654059030045</ymax>
    </bndbox>
  </object>
<object>
    <name>seven</name>
    <difficult>0</difficult>
    <bndbox>
      <xmin>36.0</xmin>
      <ymin>19.56268193078482</ymin>
      <xmax>44.0</xmax>
      <ymax>30.966294463028685</ymax>
    </bndbox>
  </object>
<object>
    <name>two</name>
    <difficult>0</difficult>
    <bndbox>
      <xmin>45.05</xmin>
      <ymin>20.036322334783463</ymin>
      <xmax>53.05</xmax>
      <ymax>31.439934867027326</ymax>
    </bndbox>
  </object>
<object>
    <name>four</name>
    <difficult>0</difficult>
    <bndbox>
      <xmin>54.1</xmin>
      <ymin>20.509962738782104</ymin>
      <xmax>62.1</xmax>
      <ymax>31.91357527102597</ymax>
    </bndbox>
  </object>
<object>
    <name>three</name>
    <difficult>0</difficult>
    <bndbox>
      <xmin>63.15</xmin>
      <ymin>20.983603142780744</ymin>
      <xmax>71.15</xmax>
      <ymax>32.387215675024606</ymax>
    </bndbox>
  </object>
</annotation>