<annotation>
  <filename>002052.jpg</filename>
  <size>
    <width>132</width>
    <height>57</height>
    <depth>3</depth>
  </size>
  <object>
    <name>three</name>
    <difficult>0</difficult>
    <bndbox>
      <xmin>17.2</xmin>
      <ymin>18.30208253125564</ymin>
      <xmax>28.2</xmax>
      <ymax>35.675621054307776</ymax>
    </bndbox>
  </object>
<object>
    <name>four</name>
    <difficult>0</difficult>
    <bndbox>
      <xmin>29.25</xmin>
      <ymin>18.722621466520774</ymin>
      <xmax>40.25</xmax>
      <ymax>36.09615998957291</ymax>
    </bndbox>
  </object>
<object>
    <name>nine</name>
    <difficult>0</difficult>
    <bndbox>
      <xmin>41.3</xmin>
      <ymin>19.143160401785913</ymin>
      <xmax>52.3</xmax>
      <ymax>36.51669892483805</ymax>
    </bndbox>
  </object>
<object>
    <name>two</name>
    <difficult>0</difficult>
    <bndbox>
      <xmin>53.35</xmin>
      <ymin>19.563699337051048</ymin>
      <xmax>64.35</xmax>
      <ymax>36.93723786010319</ymax>
    </bndbox>
  </object>
<object>
    <name>two</name>
    <difficult>0</difficult>
    <bndbox>
      <xmin>65.4</xmin>
      <ymin>19.984238272316183</ymin>
      <xmax>76.4</xmax>
      <ymax>37.35777679536832</ymax>
    </bndbox>
  </object>
<object>
    <name>six</name>
    <difficult>0</difficult>
    <bndbox>
      <xmin>77.45</xmin>
      <ymin>20.404777207581322</ymin>
      <xmax>88.45</xmax>
      <ymax>37.778315730633466</ymax>
    </bndbox>
  </object>
<object>
    <name>eight</name>
    <difficult>0</difficult>
    <bndbox>
      <xmin>89.5</xmin>
      <ymin>20.825316142846457</ymin>
      <xmax>100.5</xmax>
      <ymax>38.198854665898594</ymax>
    </bndbox>
  </object>
<object>
    <name>five</name>
    <difficult>0</difficult>
    <bndbox>
      <xmin>101.55</xmin>
      <ymin>21.245855078111596</ymin>
      <xmax>112.55</xmax>
      <ymax>38.619393601163736</ymax>
    </bndbox>
  </object>
</annotation>