<annotation>
  <filename>007800.jpg</filename>
  <size>
    <width>186</width>
    <height>73</height>
    <depth>3</depth>
  </size>
  <object>
    <name>five</name>
    <difficult>0</difficult>
    <bndbox>
      <xmin>17.55</xmin>
      <ymin>26.638688271797005</ymin>
      <xmax>37.55</xmax>
      <ymax>57.76999845387145</ymax>
    </bndbox>
  </object>
<object>
    <name>zero</name>
    <difficult>0</difficult>
    <bndbox>
      <xmin>38.6</xmin>
      <ymin>24.8040598869588</ymin>
      <xmax>58.6</xmax>
      <ymax>55.93537006903324</ymax>
    </bndbox>
  </object>
<object>
    <name>nine</name>
    <difficult>0</difficult>
    <bndbox>
      <xmin>59.65</xmin>
      <ymin>22.969431502120596</ymin>
      <xmax>79.65</xmax>
      <ymax>54.10074168419504</ymax>
    </bndbox>
  </object>
<object>
    <name>seven</name>
    <difficult>0</difficult>
    <bndbox>
      <xmin>80.7</xmin>
      <ymin>21.13480311728239</ymin>
      <xmax>100.7</xmax>
      <ymax>52.26611329935683</ymax>
    </bndbox>
  </object>
<object>
    <name>zero</name>
    <difficult>0</difficult>
    <bndbox>
      <xmin>101.75</xmin>
      <ymin>19.300174732444187</ymin>
      <xmax>121.75</xmax>
      <ymax>50.431484914518634</ymax>
    </bndbox>
  </object>
<object>
    <name>zero</name>
    <difficult>0</difficult>
    <bndbox>
      <xmin>122.8</xmin>
      <ymin>17.465546347605983</ymin>
      <xmax>142.8</xmax>
      <ymax>48.59685652968042</ymax>
    </bndbox>
  </object>
<object>
    <name>seven</name>
    <difficult>0</difficult>
    <bndbox>
      <xmin>143.85</xmin>
      <ymin>15.630917962767779</ymin>
      <xmax>163.85</xmax>
      <ymax>46.762228144842226</ymax>
    </bndbox>
  </object>
</annotation>