<annotation>
  <filename>003491.jpg</filename>
  <size>
    <width>105</width>
    <height>57</height>
    <depth>3</depth>
  </size>
  <object>
    <name>one</name>
    <difficult>0</difficult>
    <bndbox>
      <xmin>17.55</xmin>
      <ymin>22.458694330148674</ymin>
      <xmax>26.55</xmax>
      <ymax>38.78947492086856</ymax>
    </bndbox>
  </object>
<object>
    <name>two</name>
    <difficult>0</difficult>
    <bndbox>
      <xmin>27.6</xmin>
      <ymin>21.757641769020214</ymin>
      <xmax>36.6</xmax>
      <ymax>38.0884223597401</ymax>
    </bndbox>
  </object>
<object>
    <name>nine</name>
    <difficult>0</difficult>
    <bndbox>
      <xmin>37.65</xmin>
      <ymin>21.056589207891754</ymin>
      <xmax>46.65</xmax>
      <ymax>37.38736979861164</ymax>
    </bndbox>
  </object>
<object>
    <name>four</name>
    <difficult>0</difficult>
    <bndbox>
      <xmin>47.7</xmin>
      <ymin>20.355536646763294</ymin>
      <xmax>56.7</xmax>
      <ymax>36.68631723748318</ymax>
    </bndbox>
  </object>
<object>
    <name>one</name>
    <difficult>0</difficult>
    <bndbox>
      <xmin>57.75</xmin>
      <ymin>19.654484085634834</ymin>
      <xmax>66.75</xmax>
      <ymax>35.98526467635472</ymax>
    </bndbox>
  </object>
<object>
    <name>six</name>
    <difficult>0</difficult>
    <bndbox>
      <xmin>67.8</xmin>
      <ymin>18.953431524506378</ymin>
      <xmax>76.8</xmax>
      <ymax>35.28421211522626</ymax>
    </bndbox>
  </object>
<object>
    <name>nine</name>
    <difficult>0</difficult>
    <bndbox>
      <xmin>77.85</xmin>
      <ymin>18.252378963377918</ymin>
      <xmax>86.85</xmax>
      <ymax>34.583159554097804</ymax>
    </bndbox>
  </object>
</annotation>