<annotation>
  <filename>006201.jpg</filename>
  <size>
    <width>73</width>
    <height>64</height>
    <depth>3</depth>
  </size>
  <object>
    <name>six</name>
    <difficult>0</difficult>
    <bndbox>
      <xmin>19.3</xmin>
      <ymin>19.701646267402026</ymin>
      <xmax>35.3</xmax>
      <ymax>43.97722945415195</ymax>
    </bndbox>
  </object>
<object>
    <name>seven</name>
    <difficult>0</difficult>
    <bndbox>
      <xmin>36.35</xmin>
      <ymin>19.99920979715771</ymin>
      <xmax>52.35</xmax>
      <ymax>44.27479298390764</ymax>
    </bndbox>
  </object>
</annotation>