<annotation>
  <filename>007659.jpg</filename>
  <size>
    <width>125</width>
    <height>73</height>
    <depth>3</depth>
  </size>
  <object>
    <name>six</name>
    <difficult>0</difficult>
    <bndbox>
      <xmin>18.6</xmin>
      <ymin>20.0</ymin>
      <xmax>39.6</xmax>
      <ymax>53.0</ymax>
    </bndbox>
  </object>
<object>
    <name>one</name>
    <difficult>0</difficult>
    <bndbox>
      <xmin>40.65</xmin>
      <ymin>20.0</ymin>
      <xmax>61.65</xmax>
      <ymax>53.0</ymax>
    </bndbox>
  </object>
<object>
    <name>eight</name>
    <difficult>0</difficult>
    <bndbox>
      <xmin>62.7</xmin>
      <ymin>20.0</ymin>
      <xmax>83.7</xmax>
      <ymax>53.0</ymax>
    </bndbox>
  </object>
<object>
    <name>one</name>
    <difficult>0</difficult>
    <bndbox>
      <xmin>84.75</xmin>
      <ymin>20.0</ymin>
      <xmax>105.75</xmax>
      <ymax>53.0</ymax>
    </bndbox>
  </object>
</annotation>