<annotation>
  <filename>007964.jpg</filename>
  <size>
    <width>56</width>
    <height>48</height>
    <depth>3</depth>
  </size>
  <object>
    <name>seven</name>
    <difficult>0</difficult>
    <bndbox>
      <xmin>18.95</xmin>
      <ymin>20.641039886345038</ymin>
      <xmax>23.95</xmax>
      <ymax>28.272769919703006</ymax>
    </bndbox>
  </object>
<object>
    <name>four</name>
    <difficult>0</difficult>
    <bndbox>
      <xmin>25.0</xmin>
      <ymin>20.21901322019308</ymin>
      <xmax>30.0</xmax>
      <ymax>27.850743253551045</ymax>
    </bndbox>
  </object>
<object>
    <name>seven</name>
    <difficult>0</difficult>
    <bndbox>
      <xmin>31.05</xmin>
      <ymin>19.79698655404112</ymin>
      <xmax>36.05</xmax>
      <ymax>27.428716587399087</ymax>
    </bndbox>
  </object>
</annotation>