<annotation>
	<folder>JPEGImages</folder>
	<filename>001068.jpg</filename>
	<path>./VOC2007/JPEGImages/001068.jpg</path>
	<source>
		<database>Unknown</database>
	</source>
	<size>
		<width>0</width>
		<height>0</height>
		<depth>3</depth>
	</size>
	<segmented>0</segmented>
	<object>
		<name>one</name>
		<pose>Unspecified</pose>
		<truncated>0</truncated>
		<difficult>0</difficult>
		<bndbox>
			<xmin>43</xmin>
			<ymin>15</ymin>
			<xmax>274</xmax>
			<ymax>381</ymax>
		</bndbox>
	</object>
</annotation>