<annotation>
  <filename>000458.png</filename>
  <size>
    <width>125</width>
    <height>64</height>
    <depth>3</depth>
  </size>
  <object>
    <name>5</name>
    <difficult>0</difficult>
    <bndbox>
      <xmin>19.297044078605964</xmin>
      <ymin>19.743554931707855</ymin>
      <xmax>42.71270343138499</xmax>
      <ymax>45.37339908027829</ymax>
    </bndbox>
  </object>
<object>
    <name>8</name>
    <difficult>0</difficult>
    <bndbox>
      <xmin>40.293845676890186</xmin>
      <ymin>19.377054396524898</ymin>
      <xmax>63.70950502966921</xmax>
      <ymax>45.00689854509534</ymax>
    </bndbox>
  </object>
<object>
    <name>4</name>
    <difficult>0</difficult>
    <bndbox>
      <xmin>61.2906472751744</xmin>
      <ymin>19.010553861341947</ymin>
      <xmax>84.70630662795342</xmax>
      <ymax>44.64039800991239</ymax>
    </bndbox>
  </object>
<object>
    <name>5</name>
    <difficult>0</difficult>
    <bndbox>
      <xmin>82.28744887345862</xmin>
      <ymin>18.644053326158993</ymin>
      <xmax>105.70310822623765</xmax>
      <ymax>44.27389747472943</ymax>
    </bndbox>
  </object>
</annotation>