<annotation>
  <filename>007776.jpg</filename>
  <size>
    <width>161</width>
    <height>57</height>
    <depth>3</depth>
  </size>
  <object>
    <name>three</name>
    <difficult>0</difficult>
    <bndbox>
      <xmin>17.55</xmin>
      <ymin>20.0</ymin>
      <xmax>34.55</xmax>
      <ymax>37.0</ymax>
    </bndbox>
  </object>
<object>
    <name>five</name>
    <difficult>0</difficult>
    <bndbox>
      <xmin>35.6</xmin>
      <ymin>20.0</ymin>
      <xmax>52.6</xmax>
      <ymax>37.0</ymax>
    </bndbox>
  </object>
<object>
    <name>zero</name>
    <difficult>0</difficult>
    <bndbox>
      <xmin>53.65</xmin>
      <ymin>20.0</ymin>
      <xmax>70.65</xmax>
      <ymax>37.0</ymax>
    </bndbox>
  </object>
<object>
    <name>nine</name>
    <difficult>0</difficult>
    <bndbox>
      <xmin>71.7</xmin>
      <ymin>20.0</ymin>
      <xmax>88.7</xmax>
      <ymax>37.0</ymax>
    </bndbox>
  </object>
<object>
    <name>four</name>
    <difficult>0</difficult>
    <bndbox>
      <xmin>89.75</xmin>
      <ymin>20.0</ymin>
      <xmax>106.75</xmax>
      <ymax>37.0</ymax>
    </bndbox>
  </object>
<object>
    <name>eight</name>
    <difficult>0</difficult>
    <bndbox>
      <xmin>107.8</xmin>
      <ymin>20.0</ymin>
      <xmax>124.8</xmax>
      <ymax>37.0</ymax>
    </bndbox>
  </object>
<object>
    <name>zero</name>
    <difficult>0</difficult>
    <bndbox>
      <xmin>125.85</xmin>
      <ymin>20.0</ymin>
      <xmax>142.85</xmax>
      <ymax>37.0</ymax>
    </bndbox>
  </object>
</annotation>